etherunit/__init__.py
etherunit/etherunit.py
etherunit/py.typed
etherunit-0.0.6.dist-info/LICENSE
etherunit-0.0.6.dist-info/METADATA
etherunit-0.0.6.dist-info/WHEEL
etherunit-0.0.6.dist-info/top_level.txt
etherunit-0.0.6.dist-info/RECORD
