Metadata-Version: 2.1
Name: etherunit
Version: 0.0.6
Summary: Etherium unit conversation and arithmetic library
Home-page: https://github.com/yozel/etherunit
Author: Yasin Ozel
Author-email: me@yozel.co
License: UNKNOWN
Project-URL: Bug Tracker, https://github.com/yozel/etherunit/issues
Platform: UNKNOWN
Classifier: Intended Audience :: Developers
Classifier: Programming Language :: Python :: 3
Classifier: License :: OSI Approved :: Apache Software License
Classifier: Operating System :: OS Independent
Requires-Python: >=3.6
License-File: LICENSE
